TTBenchmark/__init__.py
TTBenchmark/benchmark.py
TTBenchmark/check_benchmark.py
TTBenchmark/check_environment.py
TTBenchmark/constant.py
TTBenchmark/gen_benchmark.py
TTBenchmark-0.0.1.6.2.dist-info/LICENCE
TTBenchmark-0.0.1.6.2.dist-info/METADATA
TTBenchmark-0.0.1.6.2.dist-info/WHEEL
TTBenchmark-0.0.1.6.2.dist-info/top_level.txt
TTBenchmark-0.0.1.6.2.dist-info/RECORD
