Metadata-Version: 2.1
Name: TTBenchmark
Version: 0.0.1.6.2
Summary: AIpaca TT benchmark
Home-page: UNKNOWN
Author: Yuqi Li
Author-email: yuqil@aipaca-corp.com
License: UNKNOWN
Platform: UNKNOWN
Classifier: Programming Language :: Python :: 3
Classifier: Operating System :: MacOS :: MacOS X
Classifier: Operating System :: Microsoft :: Windows
Classifier: License :: OSI Approved :: MIT License
Requires-Python: >=3.7
